securegroups/__init__.py
securegroups/admin.py
securegroups/app_settings.py
securegroups/apps.py
securegroups/auth_hooks.py
securegroups/filter.py
securegroups/models.py
securegroups/signals.py
securegroups/tasks.py
securegroups/urls.py
securegroups/views.py
securegroups/cogs/__init__.py
securegroups/cogs/groupcheck.py
securegroups/locale/de/LC_MESSAGES/django.po
securegroups/locale/en/LC_MESSAGES/django.po
securegroups/locale/uk/LC_MESSAGES/django.po
securegroups/management/commands/__init__.py
securegroups/management/commands/securegroupss_run_update.py
securegroups/management/commands/setup_securegroup_task.py
securegroups/migrations/0001_initial.py
securegroups/migrations/0002_auto_20210103_2237.py
securegroups/migrations/0003_smartfilter_grace_period.py
securegroups/migrations/0004_auto_20210104_0317.py
securegroups/migrations/0005_auto_20210104_1525.py
securegroups/migrations/0006_useringroupfilter.py
securegroups/migrations/0007_auto_20210105_0735.py
securegroups/migrations/0008_auto_20210117_0219.py
securegroups/migrations/0009_auto_20210218_0908.py
securegroups/migrations/0010_perms_update.py
securegroups/migrations/0011_smartgroup_notify_on_add_smartgroup_notify_on_grace_and_more.py
securegroups/migrations/0012_alter_pendingnotification_notified.py
securegroups/migrations/0013_useringroupfilter_reversed_logic.py
securegroups/migrations/0014_useringroupfilter_groups.py
securegroups/migrations/0015_migrate_groups.py
securegroups/migrations/0016_remove_useringroupfilter_group.py
securegroups/migrations/0017_filterexpression.py
securegroups/migrations/__init__.py
securegroups/templates/smartgroups/audit.html
securegroups/templates/smartgroups/audit_list.html
securegroups/templates/smartgroups/filter_list.html
securegroups/templates/smartgroups/groups.html
securegroups/templates/smartgroups/show_check.html
securegroups/templates/smartgroups/user_check.html
securegroups/templatetags/__init__.py
securegroups/templatetags/sg_audit.py
allianceauth_securegroups-0.9.0.dist-info/licenses/LICENSE
allianceauth_securegroups-0.9.0.dist-info/WHEEL
allianceauth_securegroups-0.9.0.dist-info/METADATA
allianceauth_securegroups-0.9.0.dist-info/RECORD
