Metadata-Version: 2.4
Name: allianceauth-securegroups
Version: 0.9.0
Summary: On its own this app does very little! However it leverages any module that is capable of providing a filter. Giving you the ability to add a very wide range of automatic filtration options your groups.
Keywords: allianceauth,eveonline
Author-email: AaronKable <aaronkable@gmail.com>
Requires-Python: >=3.8
Classifier: Environment :: Web Environment
Classifier: Framework :: Celery
Classifier: Framework :: Django
Classifier: Framework :: Django :: 4.0
Classifier: Framework :: Django :: 4.2
Classifier: Intended Audience :: Developers
Classifier: License :: OSI Approved :: MIT License
Classifier: Operating System :: OS Independent
Classifier: Programming Language :: Python
Classifier: Programming Language :: Python :: 3 :: Only
Classifier: Programming Language :: Python :: 3.8
Classifier: Programming Language :: Python :: 3.9
Classifier: Programming Language :: Python :: 3.10
Classifier: Programming Language :: Python :: 3.11
Classifier: Programming Language :: Python :: 3.12
Classifier: Programming Language :: Python :: 3.13
Classifier: Programming Language :: Python :: Implementation :: CPython
Classifier: Topic :: Internet :: WWW/HTTP
Classifier: Topic :: Internet :: WWW/HTTP :: Dynamic Content
License-File: LICENSE
Requires-Dist: allianceauth>=4,<5
Project-URL: Homepage, https://github.com/Solar-Helix-Independent-Transport/allianceauth-secure-groups
Project-URL: Source, https://github.com/Solar-Helix-Independent-Transport/allianceauth-secure-groupss
Project-URL: Tracker, https://github.com/Solar-Helix-Independent-Transport/allianceauth-secure-groups/issues
